KiCadLibrary/KiCadLibrary.py
KiCadLibrary/__init__.py
KiCadLibrary/__main__.py
KiCadLibrary/kicad_library_utils/__init__.py
KiCadLibrary/kicad_library_utils/check_lib_table.py
KiCadLibrary/kicad_library_utils/download_pretty_libs.py
KiCadLibrary/kicad_library_utils/sch/__init__.py
KiCadLibrary/kicad_library_utils/sch/add_part_number.py
KiCadLibrary/kicad_library_utils/sch/sch.py
KiCadLibrary/kicad_library_utils/sch/update_footprints.py
KiCadLibrary/kicad_library_utils/schlib/__init__.py
KiCadLibrary/kicad_library_utils/schlib/checklib.py
KiCadLibrary/kicad_library_utils/schlib/comparelibs.py
KiCadLibrary/kicad_library_utils/schlib/find_duplicates.py
KiCadLibrary/kicad_library_utils/schlib/fix-pins.py
KiCadLibrary/kicad_library_utils/schlib/fix-text-sizes.py
KiCadLibrary/kicad_library_utils/schlib/fix_footprints.py
KiCadLibrary/kicad_library_utils/schlib/move_part.py
KiCadLibrary/kicad_library_utils/schlib/move_symbols.py
KiCadLibrary/kicad_library_utils/schlib/schlib.py
robotframework_kicadlibrary-2.0.1.dist-info/LICENSE.txt
robotframework_kicadlibrary-2.0.1.dist-info/METADATA
robotframework_kicadlibrary-2.0.1.dist-info/WHEEL
robotframework_kicadlibrary-2.0.1.dist-info/top_level.txt
robotframework_kicadlibrary-2.0.1.dist-info/zip-safe
robotframework_kicadlibrary-2.0.1.dist-info/RECORD
