Metadata-Version: 2.1
Name: robotframework-kicadlibrary
Version: 2.0.1
Summary: Robot Framework KiCAD library
Home-page: https://github.com/madworx/robotframework-kicadlibrary
Author: Martin Kjellstrand
Author-email: martin.kjellstrand@madworx.se
License: MIT
Platform: UNKNOWN
Classifier: Development Status :: 4 - Beta
Classifier: Environment :: Console
Classifier: Framework :: Robot Framework :: Library
Classifier: Intended Audience :: Developers
Classifier: Intended Audience :: End Users/Desktop
Classifier: Intended Audience :: Information Technology
Classifier: Intended Audience :: Manufacturing
Classifier: License :: OSI Approved :: MIT License
Classifier: Operating System :: MacOS :: MacOS X
Classifier: Operating System :: Microsoft :: Windows
Classifier: Operating System :: POSIX
Classifier: Programming Language :: Python
Classifier: Topic :: Scientific/Engineering :: Electronic Design Automation (EDA)
Classifier: Topic :: Software Development :: Testing :: Acceptance
Requires-Dist: robotframework (<4)
